sou_eu/Desktop.png
sou_eu/Rectangle 1.png
sou_eu/__init__.py
sou_eu/thatsme.py
sou_eu-0.1.6.dist-info/LICENSE
sou_eu-0.1.6.dist-info/WHEEL
sou_eu-0.1.6.dist-info/METADATA
sou_eu-0.1.6.dist-info/RECORD
